VR503052_VR502846/Verilog/design.sv
module Morracinese(
  input [0:0] clk,
  input [1:0] g1,
  input [1:0] g2,
  input [0:0] reset, 
  output reg [1:0] manche,
  output reg [1:0] partita
);
  
  //FSM 
  reg [2:0] status = 3'b000;
  reg [2:0] nextstatus = 3'b000;
  
  //DATAPATH
  reg [4:0] mancheobb = 5'b00100;
  reg [4:0] manchecount = 5'b00000;
  reg [0:0] manchemin = 1'b0; 
  reg [0:0] manchemax = 1'b0;
  reg [1:0] precg1 = 2'b00;
  reg [1:0] precg2 = 2'b00;

  
  always @(posedge clk) begin: Updatefsm
    
    if(reset) status = 3'b000;
    else status = nextstatus;
  
  end
  
  //FSM 
  always @(manche,reset) begin: FSM 
    /*
    reset = 000
    pareggio = 001
    g1_van1 = 010 
    g1_van2 = 011
    g1_van3 = 100
    g2_van1 = 101 
    g2_van2 = 110
    g2_van3 = 111
    */
 
   case(manche)
      2'b00: begin
        if (status == 3'b000) begin
          nextstatus = 3'b000;
          partita = 2'b00;
        end 
        if (status == 3'b001) begin
        nextstatus = 3'b001;
        partita = 2'b00;
        end
      if (status == 3'b010) begin 
        nextstatus = 3'b010;
       partita = 2'b00;
        end 
      if (status == 3'b011) begin
          nextstatus = 3'b011;
       partita = 2'b00;
        end
      if (status == 3'b100) begin
          nextstatus = 3'b100;
       partita = 2'b00;
      end 
      if (status == 3'b101) begin
        nextstatus = 3'b101;
       partita = 2'b00; 
       end
      if (status == 3'b110) begin 
        nextstatus = 3'b110;
       partita = 2'b00; 
      end 
      if (status == 3'b111) begin
          nextstatus = 3'b111;
       partita = 2'b00; 
      end
   end
      
      //pareggio
      2'b11: begin
        if(status == 3'b000) begin 
         nextstatus = 3'b001; 
        partita = 2'b00;
        end
        
        if(status == 3'b001) begin
          nextstatus = 3'b001;
          if(manchemin == 1 && manchemax == 1)begin 
            partita = 2'b11;
          end
          else begin
            partita = 2'b00;
          end 
        end
        
        if (status == 3'b010) begin 
        nextstatus = 3'b010;
          if(manchemin == 1 && manchemax == 1)begin 
            partita = 2'b01;
          end
          else begin
            partita = 2'b00;
          end 
        end 
        
        if (status == 3'b011) begin 
        nextstatus = 3'b011;
          if(manchemin == 1'b1) begin
            partita = 2'b01; 
          end
          else begin
            partita = 2'b00;
          end 
        end 
    
        if (status == 3'b100) begin 
        nextstatus = 3'b100;
          if(manchemin == 1'b1) begin
            partita = 2'b01; 
          end
          else begin
            partita = 2'b00;
          end 
        end
      
      if (status == 3'b101) begin 
        nextstatus = 3'b101;
      if(manchemin == 1'b1 && manchemax == 1'b1)begin
            partita = 2'b10; 
          end
          else begin
            partita = 2'b00;
          end 
        end
        
        if (status == 3'b110) begin 
        nextstatus = 3'b110;
          if(manchemin == 1'b1 )begin
            partita = 2'b10; 
          end
          else begin
            partita = 2'b00;
          end 
        end
        
      if (status == 3'b111) begin 
        nextstatus = 3'b111;
          if(manchemin == 1'b1 )begin
            partita = 2'b10; 
          end
          else begin
            partita = 2'b00;
          end 
        end
      end
    
    
    //manche G1
      2'b01: begin
       
        if(status == 3'b000) begin
          nextstatus = 3'b010;
          partita = 2'b00;
        end
        
        if(status == 3'b001) begin 
          nextstatus = 3'b010;
          if(manchemax == 1'b1 && manchemin == 1'b1)begin
            partita = 2'b01;
          end else begin
            partita = 2'b00;
          end 
        end
        
        
        if(status == 3'b010) begin 
          nextstatus = 3'b011;
          if(manchemin == 1'b1)begin
            partita = 2'b01;
          end
            else begin
            partita = 2'b00;
          end 
        end
        
        if(status == 3'b011) begin 
          nextstatus = 3'b100;
          if(manchemin == 1'b1)begin
            partita = 2'b01;
          end
            else begin
            partita = 2'b00;
          end 
        end
          
        if(status == 3'b100) begin 
          nextstatus = 3'b100;
          if(manchemin == 1'b1)begin
            partita = 2'b01;
          end
            else begin
            partita = 2'b00;
          end 
        end
          
        if(status == 3'b101) begin 
          nextstatus = 3'b001;
           if(manchemin == 1'b1 && manchemax == 1'b1)begin
            partita = 2'b11;
           end
            else begin
            partita = 2'b00;
          end 
        end
           
         if(status == 3'b110) begin 
          nextstatus = 3'b101;
             if(manchemin == 1'b1 && manchemax == 1'b1)begin
            partita = 2'b10;
          end
            else begin
            partita = 2'b00;
          end 
        end

         if(status == 3'b111) begin 
          nextstatus = 3'b111;
             if(manchemin == 1'b1)begin
            partita = 2'b10;
             end
            else begin
            partita = 2'b00;
          end 
        end
      end
     //manche g2
        2'b10: begin   
    
        if(status == 3'b000) begin
          nextstatus = 3'b101;
          partita = 2'b00;
        end 
          
        if(status == 3'b001) begin 
          nextstatus = 3'b101;
          if(manchemax == 1'b1 && manchemin == 1'b1)begin
            partita = 2'b10;
          end
            else begin
            partita = 2'b00;
          end 
        end
        
          if(status == 3'b101) begin 
          nextstatus = 3'b110;
            if(manchemin == 1'b1)begin
            partita = 2'b10;
          end
            else begin
            partita = 2'b00;
          end 
        end
          
         if(status == 3'b110) begin 
          nextstatus = 3'b111;
           if(manchemin == 1'b1)begin
            partita = 2'b10;
          end
            else begin
            partita = 2'b00;
          end 
        end 
          
        if(status == 3'b111) begin 
          nextstatus = 3'b111;
           if(manchemin == 1'b1)begin
            partita = 2'b10;
          end
            else begin
            partita = 2'b00;
          end 
        end
         
        if(status == 3'b010) begin 
          nextstatus = 3'b001;
             if(manchemax == 1'b1 && manchemin == 1'b1)begin
            partita = 2'b10;
          end
            else begin
            partita = 2'b00;
          end 
        end
          
        if(status == 3'b011) begin 
          nextstatus = 3'b010;
             if(manchemax == 1'b1 && manchemin == 1'b1)begin
            partita = 2'b01;
          end
            else begin
            partita = 2'b00;
          end 
        end
           
           if(status == 3'b100) begin 
          nextstatus = 3'b100;
             if(manchemin == 1'b1)begin
            partita = 2'b01;
            end
              else begin
            partita = 2'b00;
          end 
        end
      end
    endcase  
  end  
       
       /*Moveset:
       
       sasso = 01
       carta = 10
       forbice = 11 
       
       */
        always @(posedge clk) begin: Datapath
         if (reset) begin
           manche = 2'b00;
           manchemin = 1'b0;
           manchemax = 1'b0;
           manchecount = 5'b00000;
           precg1 = 2'b00;
           precg2 = 2'b00;
           mancheobb = 5'b00100 + {g1,g2};
         end 
         else begin 
           if(manche != 2'b00) begin 
             manchecount++;
           end
           if (manchecount == mancheobb) begin
             manchemax = 1'b1;
           end 
           if (manchecount == 5'b00100) begin
             manchemin = 1'b1;
           end 
           
           
           if( g1 == 2'b01 && g2 == 2'b11 )begin
             if ( precg1 != 01 && precg2 !=11 ) begin
               manche = 2'b00;
             end
             manche = 2'b01;
             precg1 = 2'b01;
           end else if ( g1 == 2'b11 && g2 == 2'b01 ) begin
             if ( precg1 != 11 && precg2 !=01 ) begin
               manche = 2'b00;
             end
             manche = 2'b10;
           	 precg2 = 2'b01;
           end else if ( g1 == 2'b11 && g2 == 2'b10 ) begin
             if ( precg1 != 11 && precg2 !=10 ) begin
               manche = 2'b00;
             end
             manche = 2'b01;
           	 precg1 = 2'b11;
           end else if ( g1 == 2'b10 && g2 == 2'b11 ) begin
             if ( precg1 != 10 && precg2 !=11 ) begin
               manche = 2'b00;
             end
             manche = 2'b10;
           	 precg2 = 2'b11;
           end else if ( g1 == 2'b10 && g2 == 2'b01 ) begin
             if ( precg1 !=10 && precg2 !=01 ) begin
               manche = 2'b00;
             end
             manche = 2'b01;
           	 precg1 = 2'b10;
           end else if ( g1 == 2'b01 && g2 == 2'b10 ) begin
             if ( precg1 != 01 && precg2 != 10 ) begin
               manche = 2'b00;
             end
             manche = 2'b10;
           	 precg2 = 2'b10;
           end
         end

        end
  endmodule  
           
//comportamento dei moduli 
          
/*FSM:
la nostra FSM da in output solo e soltanto lo stato dello vittoria e tiene conto del vantaggio
*/
      
      
/*DATAPATH:
mentre nel datapath da in uscita le manche e controlla le mosse bloccanti e se la manche e valida e imposta le manche massime 
*/

VR503052_VR502846/Verilog/testbench.sv
module Testbench();

  reg [1:0] g1,g2;
  reg [0:0] reset;
  reg clk;
  
  wire [1:0] manche;
  wire [1:0] partita;
  
  //testbench script 
  integer tb;
  //verilog outputs 
  integer vout;

  Morracinese m(
    .clk(clk),
    .g1(g1),.g2(g2),.reset(reset),
    .manche(manche),.partita(partita)
  );
  
  //assegna valore contrario del clock 
  always #10 clk = ~clk;
  
  initial begin
  
    $dumpfile("dump.vcd");
    $dumpvars(1); 
  
    //genero file
    tb=$fopen("testbench.script", "w");
    vout=$fopen("outputs_verilog", "w");
    
    $fdisplay(tb,"read_blif FSMD.blif");
                
    /*Moveset:
       
       sasso = 01
       carta = 10
       forbice = 11 
       
       */            
    
                
    // play 1
    clk = 1'b0;
    reset = 1'b1;

    // manchemax = 4
    g1 = 2'b00;
    g2 = 2'b00;

    #20
    $display("play 1");
    $display("g1: %b g2: %b manche: %b partita: %b", g1, g2, manche, partita);
                $fdisplay(tb, "simulate %b %b %b %b %b", g1[1], g1[0], g2[1], g2[0],reset);
    $fdisplay(vout, "Outputs: %b %b %b %b", manche[1], manche[0], partita[1], partita[0]);
    // manche 1
    // sasso vs carta
    // manche g2
    // g2 + 1
    reset = 1'b0;
    g1 = 2'b01;
    g2 = 2'b10;
                
    
    #20
    $display("g1: %b g2: %b manche: %b partita: %b", g1, g2, manche, partita);
                $fdisplay(tb, "simulate %b %b %b %b %b", g1[1], g1[0], g2[1], g2[0],reset);
    $fdisplay(vout, "Outputs: %b %b %b %b", manche[1], manche[0], partita[1], partita[0]);
    // manche 1
    // forbice vs carta
    // manche non valida
    // g2 + 1
    g1 = 2'b11;
    g2 = 2'b10;
     
      
    #20
    $display("g1: %b g2: %b manche: %b partita: %b", g1, g2, manche, partita);
                $fdisplay(tb, "simulate %b %b %b %b %b", g1[1], g1[0], g2[1], g2[0],reset);
    $fdisplay(vout, "Outputs: %b %b %b %b", manche[1], manche[0], partita[1], partita[0]);
    // manche 2
    // sasso vs forbice
    // manche g1
    // pareggio 
    g1 = 2'b11;
    g2 = 2'b10;           
                
                
    #20
    $display("g1: %b g2: %b manche: %b partita: %b", g1, g2, manche, partita);
                $fdisplay(tb, "simulate %b %b %b %b %b", g1[1], g1[0], g2[1], g2[0],reset);
    $fdisplay(vout, "Outputs: %b %b %b %b", manche[1], manche[0], partita[1], partita[0]);
    // manche 3
    // forbice vs forbice
    // manche pareggio
    // pareggio 
    g1 = 2'b11;
    g2 = 2'b11;          
                
       
    #20
    $display("g1: %b g2: %b manche: %b partita: %b", g1, g2, manche, partita);
                $fdisplay(tb, "simulate %b %b %b %b %b", g1[1], g1[0], g2[1], g2[0],reset);
    $fdisplay(vout, "Outputs: %b %b %b %b", manche[1], manche[0], partita[1], partita[0]);
    // manche 4
    // sasso vs sasso
    // manche pareggio
    // pareggio 
    g1 = 2'b01;
    g2 = 2'b01;    
                
    
    #20
    $display("g1: %b g2: %b manche: %b partita: %b", g1, g2, manche, partita);
    $fdisplay(tb, "simulate %b %b %b %b %b", g1[1], g1[0], g2[1], g2[0],reset);
    $fdisplay(vout, "Outputs: %b %b %b %b", manche[1], manche[0], partita[1], partita[0]);
    //play vinta: pareggio   
                
                
                
    // play 2
    reset = 1'b1;

    // manchemax = 5
    g1 = 2'b00;
    g2 = 2'b01;

    #20
    $display("play 2");
    $display("g1: %b g2: %b manche: %b partita: %b", g1, g2, manche, partita);
    $fdisplay(tb, "simulate %b %b %b %b %b", g1[1], g1[0], g2[1], g2[0],reset);
    $fdisplay(vout, "Outputs: %b %b %b %b", manche[1], manche[0], partita[1], partita[0]);
    // manche 1
    // forbice vs carta
    // manche g2
    // g2 + 1
    reset = 1'b0;
    g1 = 2'b11;
    g2 = 2'b10;          
                
                
    #20
    $display("g1: %b g2: %b manche: %b partita: %b", g1, g2, manche, partita);
    $fdisplay(tb, "simulate %b %b %b %b %b", g1[1], g1[0], g2[1], g2[0],reset);
    $fdisplay(vout, "Outputs: %b %b %b %b", manche[1], manche[0], partita[1], partita[0]);
    // manche 2
    // forbice vs sasso
    // manche g2
    // g2 + 2
    g1 = 2'b11;
    g2 = 2'b01;             
                
    #20
    $display("g1: %b g2: %b manche: %b partita: %b", g1, g2, manche, partita);
    $fdisplay(tb, "simulate %b %b %b %b %b", g1[1], g1[0], g2[1], g2[0],reset);
    $fdisplay(vout, "Outputs: %b %b %b %b", manche[1], manche[0], partita[1], partita[0]);
    // manche 3
    // sasso vs forbici
    // manche g2
    // g2 + 1
    g1 = 2'b01;
    g2 = 2'b11;           
                
    #20
    $display("g1: %b g2: %b manche: %b partita: %b", g1, g2, manche, partita);
    $fdisplay(tb, "simulate %b %b %b %b %b", g1[1], g1[0], g2[1], g2[0],reset);
    $fdisplay(vout, "Outputs: %b %b %b %b", manche[1], manche[0], partita[1], partita[0]);
    // manche 4
    // forbici vs sasso
    // manche g2
    // g2 + 2
    g1 = 2'b11;
    g2 = 2'b01; 
                
    #20
    $display("g1: %b g2: %b manche: %b partita: %b", g1, g2, manche, partita);
    $fdisplay(tb, "simulate %b %b %b %b %b", g1[1], g1[0], g2[1], g2[0],reset);
    $fdisplay(vout, "Outputs: %b %b %b %b", manche[1], manche[0], partita[1], partita[0]);
    // manche 5
    // sasso vs carta
    // manche g2
    // g2 + 2
    g1 = 2'b01;
    g2 = 2'b10;   
                
    #20
    $display("g1: %b g2: %b manche: %b partita: %b", g1, g2, manche, partita);
    $fdisplay(tb, "simulate %b %b %b %b %b", g1[1], g1[0], g2[1], g2[0],reset);
    $fdisplay(vout, "Outputs: %b %b %b %b", manche[1], manche[0], partita[1], partita[0]);
    //play vinta: player g2 vantaggio 3 
                
     
    // play 3
    reset = 1'b1;

    // manchemax = 6
    g1 = 2'b01;
    g2 = 2'b10;

    #20
    $display("play 3");
    $display("g1: %b g2: %b manche: %b partita: %b", g1, g2, manche, partita);
    $fdisplay(tb, "simulate %b %b %b %b %b", g1[1], g1[0], g2[1], g2[0],reset);
    $fdisplay(vout, "Outputs: %b %b %b %b", manche[1], manche[0], partita[1], partita[0]);
    // manche 1
    // forbice vs carta
    // manche g2
    // g2 + 1
    reset = 1'b0;
    g1 = 2'b11;
    g2 = 2'b10;  
                
    #20
    $display("g1: %b g2: %b manche: %b partita: %b", g1, g2, manche, partita);
    $fdisplay(tb, "simulate %b %b %b %b %b", g1[1], g1[0], g2[1], g2[0],reset);
    $fdisplay(vout, "Outputs: %b %b %b %b", manche[1], manche[0], partita[1], partita[0]);
    // manche 2
    // carta vs forbice
    // manche g1
    // pareggio
    g1 = 2'b10;
    g2 = 2'b11;           
                
                
    #20
    $display("g1: %b g2: %b manche: %b partita: %b", g1, g2, manche, partita);
    $fdisplay(tb, "simulate %b %b %b %b %b", g1[1], g1[0], g2[1], g2[0],reset);
    $fdisplay(vout, "Outputs: %b %b %b %b", manche[1], manche[0], partita[1], partita[0]);
    // interruzione con reset durante una partita 
    reset = 1'b1;
    g1 = 2'b11;
    g2 = 2'b11;            
                
                
    //play 4
    
    //manchemax 19
    
    #20
    $display("play 4");
    $display("g1: %b g2: %b manche: %b partita: %b", g1, g2, manche, partita);
    $fdisplay(tb, "simulate %b %b %b %b %b", g1[1], g1[0], g2[1], g2[0],reset);
    $fdisplay(vout, "Outputs: %b %b %b %b", manche[1], manche[0], partita[1], partita[0]);
    // manche 1
    // sasso vs carta
    // manche g2
    // g2 + 1
    reset = 1'b0;
    g1 = 2'b01;
    g2 = 2'b10;
                
    #20
    $display("g1: %b g2: %b manche: %b partita: %b", g1, g2, manche, partita);
    $fdisplay(tb, "simulate %b %b %b %b %b", g1[1], g1[0], g2[1], g2[0],reset);
    $fdisplay(vout, "Outputs: %b %b %b %b", manche[1], manche[0], partita[1], partita[0]);
    // manche 2
    // carta vs forbice
    // manche g2
    // g2 + 2
    reset = 1'b0;
    g1 = 2'b10;
    g2 = 2'b11;
     
    #20
    $display("g1: %b g2: %b manche: %b partita: %b", g1, g2, manche, partita);
    $fdisplay(tb, "simulate %b %b %b %b %b", g1[1], g1[0], g2[1], g2[0],reset);
    $fdisplay(vout, "Outputs: %b %b %b %b", manche[1], manche[0], partita[1], partita[0]);
    // manche 3
    // forbice vs sasso
    // manche g2
    // g2 + 3
    reset = 1'b0;
    g1 = 2'b11;
    g2 = 2'b01;
                
    #20
    $display("g1: %b g2: %b manche: %b partita: %b", g1, g2, manche, partita);
    $fdisplay(tb, "simulate %b %b %b %b %b", g1[1], g1[0], g2[1], g2[0],reset);
    $fdisplay(vout, "Outputs: %b %b %b %b", manche[1], manche[0], partita[1], partita[0]);
    // manche 4
    // sasso vs carta
    // manche g2
    // g2 + 3
    reset = 1'b0;
    g1 = 2'b01;
    g2 = 2'b10; 
                
 $display("g1: %b g2: %b manche: %b partita: %b", g1, g2, manche, partita);
    $fdisplay(tb, "simulate %b %b %b %b %b", g1[1], g1[0], g2[1], g2[0],reset);
    $fdisplay(vout, "Outputs: %b %b %b %b", manche[1], manche[0], partita[1], partita[0]);
    //play vinta: player g2 vantaggio 3 
                
    $fdisplay( tb, "quit");
    $fclose(tb);            
    $fclose(vout);            
    $finish;            
   end             

endmodule

VR503052_VR502846/Verilog/dump.vcd
$date
	Thu May  9 12:44:29 2024
$end
$version
	Icarus Verilog
$end
$timescale
	1s
$end
$scope module Testbench $end
$var wire 2 ! partita [1:0] $end
$var wire 2 " manche [1:0] $end
$var reg 1 # clk $end
$var reg 2 $ g1 [1:0] $end
$var reg 2 % g2 [1:0] $end
$var reg 1 & reset $end
$var integer 32 ' tb [31:0] $end
$var integer 32 ( vout [31:0] $end
$upscope $end
$enddefinitions $end
$comment Show the parameter values. $end
$dumpall
$end
#0
$dumpvars
b10000000000000000000000000000100 (
b10000000000000000000000000000011 '
1&
b0 %
b0 $
0#
bx "
bx !
$end
#10
b0 !
b0 "
1#
#20
0#
b10 %
b1 $
0&
#30
b10 "
1#
#40
0#
b11 $
#50
b1 "
1#
#60
0#
#70
b1 "
1#
#80
0#
b11 %
#90
1#
#100
0#
b1 %
b1 $
#110
1#
#120
b1 !
0#
b0 $
1&
#130
b0 !
b0 "
1#
#140
0#
b10 %
b11 $
0&
#150
b1 "
1#
#160
0#
b1 %
#170
b10 "
1#
#180
0#
b11 %
b1 $
#190
b1 "
1#
#200
0#
b1 %
b11 $
#210
b10 "
1#
#220
0#
b10 %
b1 $
#230
1#
#240
0#
1&
#250
b0 "
1#
#260
0#
b11 $
0&
#270
b1 "
1#
#280
0#
b11 %
b10 $
#290
b10 "
1#
#300
0#
b11 $
1&
#310
b0 "
1#
#320
0#
b10 %
b1 $
0&
#330
b10 "
1#
#340
0#
b11 %
b10 $
#350
b10 "
1#
#360
0#
b1 %
b11 $
#370
b10 "
1#
#380
0#
b10 %
b1 $
